crimson/py_ts_types_beta/__init__.py
crimson/py_ts_types_beta/convert_pydantic/__init__.py
crimson/py_ts_types_beta/convert_pydantic/positive.py
crimson/py_ts_types_beta/convert_pydantic/type_util.py
crimson/py_ts_types_beta/convert_pydantic/types.py
crimson/py_ts_types_beta/convert_pydantic/utils/check.py
crimson/py_ts_types_beta/convert_pydantic/utils/comment.py
crimson/py_ts_types_beta/convert_pydantic/utils/generate_arg.py
crimson/py_ts_types_beta/convert_pydantic/utils/generate_string_field.py
crimson/py_ts_types_beta/convert_pydantic/utils/recover_annotation.py
crimson/py_ts_types_beta/convert_typing/__init__.py
crimson/py_ts_types_beta/convert_typing/negative.py
crimson/py_ts_types_beta/convert_typing/positive.py
crimson/py_ts_types_beta/convert_typing/schema.py
crimson_py_ts_types_beta-0.1.2.dist-info/METADATA
crimson_py_ts_types_beta-0.1.2.dist-info/WHEEL
crimson_py_ts_types_beta-0.1.2.dist-info/top_level.txt
crimson_py_ts_types_beta-0.1.2.dist-info/RECORD
